flit6.py
flit6-0.1.dist-info/METADATA
flit6-0.1.dist-info/WHEEL
flit6-0.1.dist-info/entry_points.txt
flit6-0.1.dist-info/top_level.txt
flit6-0.1.dist-info/RECORD
