Metadata-Version: 2.1
Name: flit6
Version: 0.1
Summary: cross-compat flit install
Home-page: https://github.com/wimglenn/flit6
Author: Wim Glenn
Author-email: hey@wimglenn.com
License: MIT
Platform: UNKNOWN
Requires-Dist: pip
Requires-Dist: flit ; python_version >= "3"
